{
    "hasDirectories": false,
    "groups": [
        "All"
    ],
    "list": [
        {
            "key": "create a keypair",
            "group": "All",
            "inputs": [
                {
                    "variable": "keypair_name",
                    "name": "Keypair name",
                    "type": "",
                    "default": ""
                }
            ]
        },
        {
            "key": "delete a keypair",
            "group": "All",
            "inputs": [
                {
                    "variable": "keypair_name",
                    "name": "Keypair name",
                    "type": "",
                    "default": ""
                }
            ]
        },
        {
            "key": "list keypairs",
            "group": "All",
            "inputs": [
                {
                    "variable": "",
                    "name": "",
                    "type": "",
                    "default": ""
                }
            ]
        }
    ]
}